ResourceMutexManager.py
setup.py
ResourceMutexManagement.egg-info/PKG-INFO
ResourceMutexManagement.egg-info/SOURCES.txt
ResourceMutexManagement.egg-info/dependency_links.txt
ResourceMutexManagement.egg-info/requires.txt
ResourceMutexManagement.egg-info/top_level.txt