Metadata-Version: 1.0
Name: ResourceMutexManagement
Version: 0.2.1
Summary: Python module for controlling concurrent access to resources
Home-page: http://code.google.com/p/resourcemutexmanagement/
Author: Henry Ashton-Martyn
Author-email: henry.ashton.martyn@gmail.com
License: MIT License
Platform: UNKNOWN
